{
    "problemId":  236,
    "title":  "二叉树的最近公共祖先",
    "slug":  "lowest-common-ancestor-of-a-binary-tree",
    "leetCodeUrl":  "https://leetcode.cn/problems/lowest-common-ancestor-of-a-binary-tree/",
    "difficulty":  "medium",
    "tags":  [
                 "tree",
                 "depth-first-search",
                 "binary-tree"
             ],
    "pattern":  "后序递归",
    "summary":  "找到二叉树中两个指定节点的最近公共祖先。",
    "coreIdea":  "抓住 后序递归 的核心不变式，按正确顺序更新状态，并在每一步处理边界情况。",
    "pitfalls":  "常见错误包括边界条件遗漏、状态更新顺序错误、重复元素处理不完整，以及把当前轮新增状态误用于当前判断。",
    "complexity":  "取决于具体实现，常见解法通常为 O(n)、O(n log n) 或网格/动态规划问题中的 O(mn)。"
}
